lncur/__init__.py
lncur/__main__.py
lncur/utils/link.py
lncur/utils/make.py
lncur-1.1.0.dist-info/METADATA
lncur-1.1.0.dist-info/WHEEL
lncur-1.1.0.dist-info/entry_points.txt
lncur-1.1.0.dist-info/licenses/LICENSE
lncur-1.1.0.dist-info/RECORD
