Metadata-Version: 2.4
Name: lncur
Version: 1.1.0
Summary: CLI tool to automate symlinking files when porting Windows cursors to Linux
Project-URL: Repository, https://github.com/claymorwan/lncur
Project-URL: Issues, https://github.com/claymorwan/lncur/issues
Project-URL: changelog, https://github.com/claymorwan/lncur/blob/main/CHANGELOG.md
Author-email: claymorwan <claymorwan@fembois.dev>
License-Expression: MIT
License-File: LICENSE
Classifier: Operating System :: POSIX :: Linux
Classifier: Programming Language :: Python :: 3
Requires-Python: >=3.13
